{"_type":"export","__export_format":4,"__export_date":"2021-01-16T21:22:08.845Z","__export_source":"insomnia.desktop.app:v2020.5.2","resources":[{"_id":"req_6683166f255644518c83f0e92e81a84a","parentId":"wrk_9a58d9c527b9468cba85ad4c07c35a4d","modified":1610832109663,"created":1610754217070,"url":"{{ base_url  }}/list_repositories?per_page=5","name":"List Repositories","description":"","method":"GET","body":{},"parameters":[],"headers":[{"name":"Authorization","value":"eyJhbGciOiJIUzI1NiJ9.eyJ1c2VyX2lkIjoxLCJleHAiOjE2MTA4NDg4NDV9.a_T2H2vRu3aKECaRE-L_40_0_vw5OI26mg1DMFBCiEs","description":"","id":"pair_abb44166751d4184bf805247717eedd6"}],"authentication":{"type":"bearer","token":"","disabled":true},"metaSortKey":-1610754217070,"isPrivate":false,"settingStoreCookies":true,"settingSendCookies":true,"settingDisableRenderRequestBody":false,"settingEncodeUrl":true,"settingRebuildPath":true,"settingFollowRedirects":"global","_type":"request"},{"_id":"wrk_9a58d9c527b9468cba85ad4c07c35a4d","parentId":null,"modified":1610753639148,"created":1610753639148,"name":"Zeedog","description":"","scope":null,"_type":"workspace"},{"_id":"req_4a930a0e89a1441eb9b70ce8a986e84f","parentId":"wrk_9a58d9c527b9468cba85ad4c07c35a4d","modified":1610830609725,"created":1610804755852,"url":"{{ base_url  }}/search_repositories?term=xpto&language=xrubi","name":"Search Repositories","description":"","method":"GET","body":{},"parameters":[],"headers":[{"name":"Authorization","value":"eyJhbGciOiJIUzI1NiJ9.eyJ1c2VyX2lkIjoxLCJleHAiOjE2MTA4NDg4NDV9.a_T2H2vRu3aKECaRE-L_40_0_vw5OI26mg1DMFBCiEs","description":"","id":"pair_abb44166751d4184bf805247717eedd6"}],"authentication":{"type":"bearer","token":"","disabled":true},"metaSortKey":-1600175623374,"isPrivate":false,"settingStoreCookies":true,"settingSendCookies":true,"settingDisableRenderRequestBody":false,"settingEncodeUrl":true,"settingRebuildPath":true,"settingFollowRedirects":"global","_type":"request"},{"_id":"req_f52e4ec5ec7f44199f9dc9bca8a67ff7","parentId":"wrk_9a58d9c527b9468cba85ad4c07c35a4d","modified":1610754210103,"created":1610753639181,"url":"{{ base_url  }}/auth","name":"Auth","description":"","method":"POST","body":{"mimeType":"application/json","text":"{\n\t\"email\": \"demo@demo.com\",\n\t\"password\": \"demo\"\n}"},"parameters":[],"headers":[{"id":"pair_90de22cf2b3d4863a2532f51830caf78","name":"Content-Type","value":"application/json"}],"authentication":{"type":"bearer"},"metaSortKey":-1587059401430,"isPrivate":false,"settingStoreCookies":true,"settingSendCookies":true,"settingDisableRenderRequestBody":false,"settingEncodeUrl":true,"settingRebuildPath":true,"settingFollowRedirects":"global","_type":"request"},{"_id":"env_759b8d26ea1b4391ba4336f3cf8d2c08","parentId":"wrk_9a58d9c527b9468cba85ad4c07c35a4d","modified":1610753639156,"created":1610753639156,"name":"Base Environment","data":{},"dataPropertyOrder":{},"color":null,"isPrivate":false,"metaSortKey":1580318440443,"_type":"environment"},{"_id":"jar_34c6ac6a0d9a4bdeaf73c8820d2664cc","parentId":"wrk_9a58d9c527b9468cba85ad4c07c35a4d","modified":1610753639171,"created":1610753639171,"name":"Default Jar","cookies":[{"creation":"2020-04-27T14:31:43.345Z","domain":"twitter.com","expires":"2022-04-27T14:31:43.000Z","extensions":["SameSite=None"],"hostOnly":false,"id":"49038787652174864","key":"personalization_id","lastAccessed":"2020-04-27T14:31:43.345Z","maxAge":63072000,"path":"/","secure":true,"value":"\"v1_R3SgpluiKGCAnR1rRjIbXQ==\""},{"creation":"2020-04-27T14:31:43.347Z","domain":"twitter.com","expires":"2022-04-27T14:31:43.000Z","extensions":["SameSite=None"],"hostOnly":false,"id":"7499355468465856","key":"guest_id","lastAccessed":"2020-04-27T14:31:43.347Z","maxAge":63072000,"path":"/","secure":true,"value":"v1%3A158799790321122730"},{"creation":"2020-04-27T14:34:37.780Z","domain":"twitter.com","expires":"2020-04-27T14:34:43.000Z","hostOnly":false,"httpOnly":true,"id":"03224333957948211","key":"fm","lastAccessed":"2020-04-27T14:34:43.433Z","maxAge":0,"path":"/","secure":true,"value":"0"},{"creation":"2020-04-27T14:34:37.780Z","domain":"twitter.com","hostOnly":false,"httpOnly":true,"id":"44476339603506365","key":"_twitter_sess","lastAccessed":"2020-04-27T14:34:43.434Z","path":"/","secure":true,"value":"BAh7CSIKZmxhc2hJQzonQWN0aW9uQ29udHJvbGxlcjo6Rmxhc2g6OkZsYXNo%250ASGFzaHsABjoKQHVzZWR7ADoPY3JlYXRlZF9hdGwrCMmxD7xxAToMY3NyZl9p%250AZCIlZjBiNzc1MzlkMTZhODJjNDI1YjFkMGJhYzlkYjU4NGM6B2lkIiUxMWM3%250AOWFkYjA0ZjBhOTA4YmVmY2Q0MTgxZDBmNjkxYw%253D%253D--0dddd06c240a90d908e4cda8979ccdc450333e41"}],"_type":"cookie_jar"},{"_id":"spc_189e4a5dd1a64ff282e2838f6d9dc053","parentId":"wrk_9a58d9c527b9468cba85ad4c07c35a4d","modified":1610753639176,"created":1610753639176,"fileName":"MarkePlaceAPI","contents":"","contentType":"yaml","_type":"api_spec"},{"_id":"env_d3ae625a0256412f8d80951f7076b53a","parentId":"env_759b8d26ea1b4391ba4336f3cf8d2c08","modified":1610753639158,"created":1610753639158,"name":"dev","data":{"base_url":"http://localhost:3000/api/v1/"},"dataPropertyOrder":{"&":["base_url"]},"color":"#00f900","isPrivate":false,"metaSortKey":1586802541205,"_type":"environment"},{"_id":"env_a89660537b23411686597d85925e9a3f","parentId":"env_759b8d26ea1b4391ba4336f3cf8d2c08","modified":1610753639163,"created":1610753639163,"name":"prod","data":{"base_url":"http://localhost:3000/api/v1/"},"dataPropertyOrder":{"&":["base_url"]},"color":"#ff2600","isPrivate":false,"metaSortKey":1586802596623,"_type":"environment"}]}